pocketing/__init__.py
pocketing/constants.py
pocketing/contour.py
pocketing/exchange.py
pocketing/graph.py
pocketing/grid.py
pocketing/polygons.py
pocketing/spiral.py
pocketing/toolpath.py
pocketing/trochoidal.py
pocketing/version.py
pocketing/visualize.py
pocketing-0.0.17.dist-info/LICENSE
pocketing-0.0.17.dist-info/METADATA
pocketing-0.0.17.dist-info/WHEEL
pocketing-0.0.17.dist-info/top_level.txt
pocketing-0.0.17.dist-info/RECORD
