Metadata-Version: 2.1
Name: pocketing
Version: 0.0.17
Summary: Generate 2D toolpaths from polygons
Home-page: http://github.com/mikedh/pocketing
Author: Michael Dawson-Haggerty
Author-email: mikedh@kerfed.com
License: MIT
Keywords: graphics mesh geometry 3D
Platform: UNKNOWN
Classifier: Development Status :: 3 - Alpha
Classifier: License :: OSI Approved :: MIT License
Classifier: Programming Language :: Python
Classifier: Programming Language :: Python :: 3.5
Classifier: Programming Language :: Python :: 3.6
Classifier: Programming Language :: Python :: 3.7
Classifier: Natural Language :: English
Classifier: Topic :: Scientific/Engineering
Requires-Dist: numpy
Requires-Dist: scipy
Requires-Dist: rtree
Requires-Dist: shapely
Requires-Dist: networkx
Requires-Dist: trimesh
